Metadata-Version: 2.1
Name: findr2
Version: 0.0.2
Summary: With This Library You Can Find The Best Random State For Your Model 
Home-page: UNKNOWN
Author-email: ranjitmaity95@gmail.com
License: UNKNOWN
Platform: UNKNOWN
